README.txt
setup.py
collective/__init__.py
collective.contentrules.mailadapter.egg-info/PKG-INFO
collective.contentrules.mailadapter.egg-info/SOURCES.txt
collective.contentrules.mailadapter.egg-info/dependency_links.txt
collective.contentrules.mailadapter.egg-info/entry_points.txt
collective.contentrules.mailadapter.egg-info/namespace_packages.txt
collective.contentrules.mailadapter.egg-info/not-zip-safe
collective.contentrules.mailadapter.egg-info/requires.txt
collective.contentrules.mailadapter.egg-info/top_level.txt
collective/contentrules/__init__.py
collective/contentrules/mailadapter/__init__.py
collective/contentrules/mailadapter/configure.zcml
collective/contentrules/mailadapter/interfaces.py
collective/contentrules/mailadapter/actions/__init__.py
collective/contentrules/mailadapter/actions/configure.zcml
collective/contentrules/mailadapter/actions/mail.py
docs/HISTORY.txt