Metadata-Version: 1.0
Name: collective.contentrules.mailadapter
Version: 1.0
Summary: A mail content rule action using an adapter for emails resolving
Home-page: http://pypi.python.org/pypi/collective.contentrules.mailadapter
Author: Matous Hora (DMS4u)
Author-email: matous.hora@dms4u.cz
License: GPL
Keywords: plone content rule mail adapter
Platform: UNKNOWN
Classifier: Programming Language :: Python
Classifier: Topic :: Software Development :: Libraries :: Python Modules
